{
	"leltes" :
	{
		"class" : "sculptor",
		"female" : false,
		"texts" :
		{
			"name" : "Leltes",
			"biography" : "Leltes is a seasoned warrior who has fought in many battles and is convinced that good armor is the key to survival.",
			"specialty" :
			{
				"description" : "{Armorer}\r\n\r\nReceives a 5% per level bonus to Armorer skill.",
				"tooltip" : "Secondary Skill Bonus: Armorer",
				"name" : "Armorer"
			}
		},
		"images" :
		{
			"specialtySmall" : "court/heroes/leltes/spec-small.png",
			"specialtyLarge" : "court/heroes/leltes/spec-large.png",
			"large" : "court/heroes/leltes/portrait-large.png",
			"small" : "court/heroes/leltes/portrait-small.png"
		},
		"army" :
		[
			{ "creature" : "culv1", "min" : 12, "max" : 25 },
			{ "creature" : "culv2", "min" : 6, "max" : 11 },
			{ "creature" : "culv3", "min" : 3, "max" : 5}
		],
		"skills" : [
			{
				"level" : "basic",
				"skill" : "armorer"
			},
			{
				"level" : "basic",
				"skill" : "tactics"
			}
		],
		"specialty" : {
			"secondary" : "armorer"
		}		
	}
}
